fshow/__init__.py
fshow/core.py
fshow/fshow.py
fshow-0.1.0.dist-info/licenses/LICENSE
fshow-0.1.0.dist-info/METADATA
fshow-0.1.0.dist-info/WHEEL
fshow-0.1.0.dist-info/entry_points.txt
fshow-0.1.0.dist-info/top_level.txt
fshow-0.1.0.dist-info/RECORD
