Metadata-Version: 2.4
Name: fshow
Version: 0.1.0
Summary: The best library for viewing files over multiple languages.
Author-email: Blanchard Dimitri <dimitriblanchard@proton.me>
Project-URL: Homepage, https://github.com/Dimitri-Blanchard/fshow
Classifier: Programming Language :: Python :: 3
Classifier: License :: OSI Approved :: MIT License
Classifier: Operating System :: OS Independent
Classifier: Topic :: System :: Filesystems
Classifier: Environment :: Console
Requires-Python: >=3.7
License-File: LICENSE
Requires-Dist: rich>=10.0
Dynamic: license-file
